{
  "date": "2026-08-08",
  "name": "Croft",
  "width": 15,
  "height": 20,
  "laser": {"x": 4, "y": 19, "dir": "up"},
  "num_mirrors": 10,
  "obstacle_groups": [
    {"label": "NW corner", "cells": [[0,0],[1,0],[0,1],[1,1]]},
    {"label": "NE corner", "cells": [[13,0],[14,0],[14,1]]},
    {"label": "SW corner", "cells": [[0,17],[0,18],[0,19],[1,19]]},
    {"label": "SE corner", "cells": [[14,18],[14,19]]},
    {"label": "run-breaker", "cells": [[3,10],[4,10]]},
    {"label": "upper-left L", "cells": [[5,3],[6,3],[5,4]]},
    {"label": "upper-right S", "cells": [[9,4],[10,4],[10,5],[11,5]]},
    {"label": "mid-left L", "cells": [[1,7],[2,7],[2,8]]},
    {"label": "mid-right L", "cells": [[12,7],[12,8],[13,8]]},
    {"label": "center L", "cells": [[6,12],[7,12],[7,13]]},
    {"label": "lower-right L", "cells": [[9,13],[10,13],[9,14]]}
  ],
  "splitters": [],
  "gates": [
    {"x": 0, "y": 9, "dir": "up"},
    {"x": 0, "y": 15, "dir": "down"},
    {"x": 14, "y": 6, "dir": "up"},
    {"x": 14, "y": 13, "dir": "down"}
  ]
}
